register/register.v
module register (
    input [31:0] d,
    input clk, en,
    output reg [31:0] q
);
    // Initialize register to zero on start
    initial q = 32'h00000000;

    // Update q on positive edge of clock
    always @ (posedge clk) begin
        if (en == 1'b1) q <= d;
    end
endmodule

register/register_tb.v
`timescale 1ns/1ps

module register_tb ();
    // Test inputs
    reg [31:0] d;
    reg clk;
    reg en;

    // Output
    wire [31:0] q;

    // Instantiate unit under test (uut)
    register uut (
        d,
        clk,
        en,
        q
    );

    // Clock generation | every 5ns switch between high/low
    always #5 clk = ~clk;

    initial begin
        $dumpfile("register_tb.vcd"); // Waveform
        $dumpvars(0, register_tb);

        // Initialize signals
        clk = 0;
        en = 0; // Disabled on start
        d = 32'h00000000;
        #10 // wait for one clock cycle low->high

        d = 32'hFFFFFFFF;
        #10

        d = 32'h0F0F0F0F;
        #10

        en = 1; // Enabled here
        d = 32'hFFFFFFFF;
        #10

        d = 32'h0F0F0F0F;
        #10

        d = 32'h00000000;
        #10

        $finish;
    end
endmodule

register/register_tb.vcd
$date
	Tue Feb 18 10:57:30 2025
$end
$version
	Icarus Verilog
$end
$timescale
	1ps
$end
$scope module register_tb $end
$var wire 32 ! q [31:0] $end
$var reg 1 " clk $end
$var reg 32 # d [31:0] $end
$var reg 1 $ en $end
$scope module uut $end
$var wire 1 " clk $end
$var wire 32 % d [31:0] $end
$var wire 1 $ en $end
$var reg 32 & q [31:0] $end
$upscope $end
$upscope $end
$enddefinitions $end
$comment Show the parameter values. $end
$dumpall
$end
#0
$dumpvars
b0 &
b0 %
0$
b0 #
0"
b0 !
$end
#5000
1"
#10000
0"
b11111111111111111111111111111111 #
b11111111111111111111111111111111 %
#15000
1"
#20000
0"
b1111000011110000111100001111 #
b1111000011110000111100001111 %
#25000
1"
#30000
0"
b11111111111111111111111111111111 #
b11111111111111111111111111111111 %
1$
#35000
b11111111111111111111111111111111 !
b11111111111111111111111111111111 &
1"
#40000
0"
b1111000011110000111100001111 #
b1111000011110000111100001111 %
#45000
b1111000011110000111100001111 !
b1111000011110000111100001111 &
1"
#50000
0"
b0 #
b0 %
#55000
b0 !
b0 &
1"
