extend/extend.v
module extend (
    input [31:7] imm_in,
    input [2:0] extend_ctrl,
    output reg [31:0] imm_out
);

    always @(imm_in, extend_ctrl) begin
        case (extend_ctrl)
            3'b000: begin // I-Type (Immediate)
                imm_out = { { 20{imm_in[31]} }, imm_in[31:20]};
            end
            3'b001: begin // S-Type (Stores)
                imm_out = { { 13{imm_in[31]} }, imm_in[31:25], imm_in[11:7] };
            end
            3'b010: begin // B-Type (Branch)
                // * LSB bit is 0 for word alignment (branch type)
                imm_out = { { 19{imm_in[31]} }, imm_in[31], imm_in[7], imm_in[30:25], imm_in[11:8], 1'b0 };
            end
            3'b011: begin // U-Type (Upper Immediate)
                // * lower 12 bits are always 0s
                imm_out = { imm_in[31:12], 12'b0};
            end
            3'b100: begin // J-Type (Jump)
                // * LSB is 0 for word alignment (jump type)
                imm_out = { { 11{imm_in[31]} } , imm_in[31], imm_in[19:12], imm_in[20], imm_in[30:21], 1'b0 };
            end
            default: begin // X
                imm_out = 32'b0;
            end
        endcase
    end
    
endmodule

extend/extend_tb.v
module extend_tb ();
    reg [24:0] imm_in;
    reg [2:0] extend_ctrl;
    wire [31:0] imm_out;

    extend uut(
        imm_in,
        extend_ctrl,
        imm_out
    );

    task assert_test(
        input [127:0] label,
        input [24:0] imm_in,
        input [31:0] imm_out,
        input [31:0] expected
    ); begin
        $display("============================================");
        $display("Imm In  : %b", imm_in);
        $display("Imm Out : %b", imm_out);
        $display("Expected: %b", expected);
        if (imm_out != expected)
            $display("%0s: FAIL", label);
        else
            $display("%0s: PASS", label);
        $display("============================================");
        end
    endtask

    initial begin
        $dumpfile("extend_tb.vcd");
        $dumpvars(0, extend_tb);

        // Test cases (imm_in is only bits [31:7] of the instruction)

        // ========= Case I-Type ============================================
        // Immediate Type - 20 Bit Sign Extension + Bits 31 to 20
        // ==================================================================
        // Case I-Type : Positive Value
        imm_in = 25'b000000000001_0000000000000; extend_ctrl = 3'b000; #10;
        assert_test("I-TYPE POS    ", imm_in, imm_out, { 20'b0, 12'b000000000001 });

        // Case I-Type : Maximum Positive Value
        imm_in = 25'b011111111111_1111111111111; #10;
        assert_test("I-TYPE MAX POS", imm_in, imm_out, { 20'b0, 12'b011111111111 });

        // Case I-Type : Maximum Negative Value
        imm_in = 25'b100000000000_0000000000000; #10;
        assert_test("I-TYPE MAX NEG", imm_in, imm_out, { ~20'b0, 12'b100000000000 });


        // ========= Case S-Type ============================================
        // Store Type - 13 Bit Sign Extension +  Bits 31 to 25 + Bits 11 to 7
        // ==================================================================
        // Case S-Type : Positive Value
        imm_in = 25'b0000000_0000001111111_11111; extend_ctrl = 3'b001; #10;
        assert_test("S-TYPE POS    ", imm_in, imm_out, { 
            13'b0, // Sign extension
            7'b0000000, // Bits 31 to 25
            5'b11111 // Bits 11 to 7
        });

        // Case S-Type : Negative Value
        imm_in = 25'b1111100_0000001111111_10101; extend_ctrl = 3'b001; #10;
        assert_test("S-TYPE NEG    ", imm_in, imm_out, { 
            ~13'b0, // Sign extension
            7'b1111100, // Bits 31 to 25
            5'b10101 // Bits 11 to 7
        });


        // ========= Case B-Type ============================================
        // Branch Type - 19 Bit Sign Extension + Bit 31 + Bit 7 + Bits 30 to 25 + Bits 11 to 8 + 0
        // ==================================================================
        // Case B-Type (Branch Type - Positive Value)
        imm_in = 25'b0_000000_0000001111111_1111_1; extend_ctrl = 3'b010; #10;
        assert_test("B-TYPE POS    ", imm_in, imm_out, {
            19'b0, // Sign extension
            1'b0, // Bit 31
            1'b1, // Bit 7
            6'b000000, // Bits 30 to 25
            4'b1111, // Bits 11 to 8
            1'b0 // 0 for word alignment
        });

        // Case B-Type (Branch Type - Negative Value)
        imm_in = 25'b1_000011_0000001111111_1111_0; extend_ctrl = 3'b010; #10;
        assert_test("B-TYPE NEG    ", imm_in, imm_out, {
            ~19'b0, // Sign extension
            1'b1, // Bit 31
            1'b0, // Bit 7
            6'b000011, // Bits 30 to 25
            4'b1111, // Bits 11 to 8
            1'b0 // 0 for word alignment
        });


        // ========= Case U-Type ============================================
        // Upper Immediate Type - Upper Bits 31 to 12 + Lower Extended 0s
        // Note: Immediate Value is Unsigned
        // ==================================================================
        // Case U-Type : Maximum Positive Value
        imm_in = 25'b11111111111111111111_00000; extend_ctrl = 3'b011; #10;
        assert_test("U-TYPE MAX POS", imm_in, imm_out, {
            20'b11111111111111111111, // Upper Bits 31 to 12
            12'b0 // Lower Extended Zeros
        });


        // ========= Case J-Type ============================================
        // Case J-Type (Jump Type - 11 Bit Sign Extension + Bit 31 + Bits 19 to 12 + Bit 20 + Bits 30 to 21 + 0)
        // ==================================================================
        // Case J-Type : Maximum Positive Value
        imm_in = 25'b0_1111111111_1_11111111_11111; extend_ctrl = 3'b100; #10;
        assert_test("J-TYPE MAX POS", imm_in, imm_out, {
            11'b0, // Sign extension
            1'b0, // Bit 31
            8'b11111111, // Bits 19 to 12
            1'b1, // Bit 20
            10'b1111111111, // Bits 30 to 21
            1'b0 // 0 for word alignment
        });

        // Case J-Type : Maximum Negative Value
        imm_in = 25'b1_0000000000_0_00000000_11111; extend_ctrl = 3'b100; #10;
        assert_test("J-TYPE MAX NEG", imm_in, imm_out, {
            ~11'b0, // Sign extension
            1'b1, // Bit 31
            8'b00000000, // Bits 19 to 12
            1'b0, // Bit 20
            10'b0000000000, // Bits 30 to 21
            1'b0 // 0 for word alignment
        });

        $finish;
    end

endmodule

extend/extend_tb.vcd
$date
	Sat Mar 15 19:57:30 2025
$end
$version
	Icarus Verilog
$end
$timescale
	1s
$end
$scope module extend_tb $end
$var wire 32 ! imm_out [31:0] $end
$var reg 3 " extend_ctrl [2:0] $end
$var reg 25 # imm_in [24:0] $end
$scope module uut $end
$var wire 3 $ extend_ctrl [2:0] $end
$var wire 25 % imm_in [31:7] $end
$var reg 32 & imm_out [31:0] $end
$upscope $end
$scope task assert_test $end
$var reg 32 ' expected [31:0] $end
$var reg 25 ( imm_in [24:0] $end
$var reg 32 ) imm_out [31:0] $end
$var reg 128 * label [127:0] $end
$upscope $end
$upscope $end
$enddefinitions $end
$comment Show the parameter values. $end
$dumpall
$end
#0
$dumpvars
bx *
bx )
bx (
bx '
b1 &
b10000000000000 %
b0 $
b10000000000000 #
b0 "
b1 !
$end
#10
b11111111111 !
b11111111111 &
b111111111111111111111111 #
b111111111111111111111111 %
b1 '
b1 )
b10000000000000 (
b100100100101101010101000101100101010000010001010010000001010000010011110101001100100000001000000010000000100000 *
#20
b11111111111111111111100000000000 !
b11111111111111111111100000000000 &
b1000000000000000000000000 #
b1000000000000000000000000 %
b11111111111 '
b11111111111 )
b111111111111111111111111 (
b100100100101101010101000101100101010000010001010010000001001101010000010101100000100000010100000100111101010011 *
#30
b11111 !
b11111 &
b1 "
b1 $
b111111111111 #
b111111111111 %
b11111111111111111111100000000000 '
b11111111111111111111100000000000 )
b1000000000000000000000000 (
b100100100101101010101000101100101010000010001010010000001001101010000010101100000100000010011100100010101000111 *
#40
b1111111111111111110010101 !
b1111111111111111110010101 &
b1111100000000111111110101 #
b1111100000000111111110101 %
b11111 '
b11111 )
b111111111111 (
b101001100101101010101000101100101010000010001010010000001010000010011110101001100100000001000000010000000100000 *
#50
b100000011110 !
b100000011110 &
b10 "
b10 $
b111111111111 #
b111111111111 %
b1111111111111111110010101 '
b1111111111111111110010101 )
b1111100000000111111110101 (
b101001100101101010101000101100101010000010001010010000001001110010001010100011100100000001000000010000000100000 *
#60
b11111111111111111111000001111110 !
b11111111111111111111000001111110 &
b1000011000000111111111110 #
b1000011000000111111111110 %
b100000011110 '
b100000011110 )
b111111111111 (
b100001000101101010101000101100101010000010001010010000001010000010011110101001100100000001000000010000000100000 *
#70
b11111111111111111111000000000000 !
b11111111111111111111000000000000 &
b11 "
b11 $
b1111111111111111111100000 #
b1111111111111111111100000 %
b11111111111111111111000001111110 '
b11111111111111111111000001111110 )
b1000011000000111111111110 (
b100001000101101010101000101100101010000010001010010000001001110010001010100011100100000001000000010000000100000 *
#80
b11111111111111111110 !
b11111111111111111110 &
b100 "
b100 $
b111111111111111111111111 #
b111111111111111111111111 %
b11111111111111111111000000000000 '
b11111111111111111111000000000000 )
b1111111111111111111100000 (
b101010100101101010101000101100101010000010001010010000001001101010000010101100000100000010100000100111101010011 *
#90
b11111111111100000000000000000000 !
b11111111111100000000000000000000 &
b1000000000000000000011111 #
b1000000000000000000011111 %
b11111111111111111110 '
b11111111111111111110 )
b111111111111111111111111 (
b100101000101101010101000101100101010000010001010010000001001101010000010101100000100000010100000100111101010011 *
#100
b11111111111100000000000000000000 '
b11111111111100000000000000000000 )
b1000000000000000000011111 (
b100101000101101010101000101100101010000010001010010000001001101010000010101100000100000010011100100010101000111 *
