alu/alu.v
module alu(
    input signed [31:0] A, B,
    input [2:0] ALUControl,
    output reg signed [31:0] Result,
    output reg V, N, Zero
);

    always @(A, B, ALUControl) begin
        case (ALUControl)
            3'b000: begin // ADD
                Result = A + B;
            end
            3'b001: begin // SUB
                Result = A - B;
            end
            3'b010: begin // AND
                Result = A & B;
            end
            3'b011: begin // OR
                Result = A | B;
            end
            3'b100: begin // XOR
                Result = A ^ B;
            end
            3'b101: begin // SLL
                Result = A << B;
            end
            3'b110: begin // SRL
                Result = A >> B;
            end
            3'b111: begin // SLT
                if (A - B < 0)
                    // Set Less Than to 1
                    Result = 32'd1;
                else
                    // Set Less Than to 0
                    Result = 32'd0;
            end
            default:
                Result = 0;
        endcase

        if (A - B < 0) begin
            N <= 1;
            Zero <= 0;
        end else if (A - B == 0) begin
            Zero <= 1;
            N <= 0;
            V <= 0;
        end else begin
            V <= 0;
            N <= 0;
            Zero <= 0;
        end
    end
endmodule

alu/alu_tb.v
module alu_tb ();
    // test inputs
    reg signed [31:0] A, B;
    reg [2:0] ALUControl;

    // test outputs
    wire signed [31:0] Result;
    wire V, N, Zero;

    alu uut(
        A,
        B,
        ALUControl,
        Result,
        V,
        N,
        Zero
    );

    // Task for test assertion
    task assert_test(
        input [127:0] label,
        input signed [31:0] expected,
        input use_bin
    );
        begin
            $display("==================================================");
            $display("%0s", label);

            if (use_bin) begin
                $display("A:        %b", A);
                $display("B:        %b", B);
                $display("Expected: %b", expected);
                $display("Result:   %b", Result);
            end else begin
                $display("A:        %d", A);
                $display("B:        %d", B);
                $display("Expected: %d", expected);
                $display("Result:   %d", Result);
            end

            $display("Flags: V(%b), N(%b), Zero(%b)", V, N, Zero);
            
            if (Result != expected) begin
                $display("❌ Test Failed! Expected: %0d, Got: %0d", expected, Result);
            end else if (A - B < 0 && N != 1) begin
                $display("❌ Test Failed! Expected N: 1, Got N: %0d", N);
            end else if (A - B == 0 && Zero != 1) begin
                $display("❌ Test Failed! Expected Zero: 1, Got Zero: %0d", Zero);
            end else begin
                $display("✅ Test Passed!");
            end
        end
    endtask

    initial begin
        $dumpfile("alu_tb.vcd");
        $dumpvars(0, alu_tb);

        // ADD +A +B
        ALUControl = 3'b000;
        A = 32'd124;
        B = 32'd73;
        #10
        assert_test("ADD +A +B", 124+73, 0);

        // ADD +A -B
        ALUControl = 3'b000;
        A = 32'd124;
        B = -32'd73;
        #10
        assert_test("ADD +A -B", 124+(-73), 0);

        // ADD -A -B
        ALUControl = 3'b000;
        A = -32'd124;
        B = -32'd73;
        #10
        assert_test("ADD -A -B", -124+(-73), 0);

        // SUB A > B
        A = 32'd124;
        B = 32'd73;
        ALUControl = 3'b001;
        #10
        assert_test("SUB A > B", 124-73, 0);

        // SUB A < B
        A = 32'd20;
        B = 32'd120;
        ALUControl = 3'b001;
        #10
        assert_test("SUB A < B", 20-120, 0);

        // SUB A == B
        A = 32'd124;
        B = 32'd124;
        ALUControl = 3'b001;
        #10
        assert_test("SUB A == B", 124-124, 0);

        // SUB A - (-B)
        A = 32'd20;
        B = -32'd120;
        ALUControl = 3'b001;
        #10
        assert_test("SUB A - (-B)", 20-(-120), 0);

        // SUB A - (-B)
        A = -32'd20;
        ALUControl = 3'b001;
        #10
        assert_test("SUB -A - (-B)", -20-(-120), 0);

        // AND
        A = 32'd124;
        B = 32'd73;
        ALUControl = 3'b010;
        #10
        assert_test("AND", 32'd124 & 32'd73, 1);

        // OR
        ALUControl = 3'b011;
        #10
        $display("OR Result: %0b", Result);
        assert_test("OR", 32'd124 | 32'd73, 1);

        // XOR
        ALUControl = 3'b100;
        #10
        $display("XOR Result: %0b", Result);
        assert_test("XOR", 32'd124 ^ 32'd73, 1);

        // SLL
        B = 5; 
        ALUControl = 3'b101;
        #10
        assert_test("SLL", 32'd124 << 5, 1);

        // SRL
        ALUControl = 3'b110;
        #10
        assert_test("SRL", 32'd124 >> 5, 1);

        // A LESS THAN B
        ALUControl = 3'b111;
        #10
        $display("SLT Result: %0b", Result);

        $finish;
    end
endmodule

alu/alu_tb.vcd
$date
	Wed Feb 26 17:47:39 2025
$end
$version
	Icarus Verilog
$end
$timescale
	1s
$end
$scope module alu_tb $end
$var wire 1 ! Zero $end
$var wire 1 " V $end
$var wire 32 # Result [31:0] $end
$var wire 1 $ N $end
$var reg 32 % A [31:0] $end
$var reg 3 & ALUControl [2:0] $end
$var reg 32 ' B [31:0] $end
$scope module uut $end
$var wire 32 ( A [31:0] $end
$var wire 3 ) ALUControl [2:0] $end
$var wire 32 * B [31:0] $end
$var reg 1 $ N $end
$var reg 32 + Result [31:0] $end
$var reg 1 " V $end
$var reg 1 ! Zero $end
$upscope $end
$scope task assert_test $end
$var reg 32 , expected [31:0] $end
$var reg 128 - label [127:0] $end
$var reg 1 . use_bin $end
$upscope $end
$upscope $end
$enddefinitions $end
#0
$dumpvars
x.
bx -
bx ,
b11000101 +
b1001001 *
b0 )
b1111100 (
b1001001 '
b0 &
b1111100 %
0$
b11000101 #
0"
0!
$end
#10
b110011 #
b110011 +
b11111111111111111111111110110111 '
b11111111111111111111111110110111 *
0.
b11000101 ,
b10000010100010001000100001000000010101101000001001000000010101101000010 -
#20
1$
b11111111111111111111111100111011 #
b11111111111111111111111100111011 +
b11111111111111111111111110000100 %
b11111111111111111111111110000100 (
b110011 ,
b10000010100010001000100001000000010101101000001001000000010110101000010 -
#30
0$
b110011 #
b110011 +
b1 &
b1 )
b1001001 '
b1001001 *
b1111100 %
b1111100 (
b11111111111111111111111100111011 ,
b10000010100010001000100001000000010110101000001001000000010110101000010 -
#40
1$
b11111111111111111111111110011100 #
b11111111111111111111111110011100 +
b1111000 '
b1111000 *
b10100 %
b10100 (
b110011 ,
b10100110101010101000010001000000100000100100000001111100010000001000010 -
#50
0$
1!
b0 #
b0 +
b1111100 '
b1111100 *
b1111100 %
b1111100 (
b11111111111111111111111110011100 ,
b10100110101010101000010001000000100000100100000001111000010000001000010 -
#60
0!
b10001100 #
b10001100 +
b11111111111111111111111110001000 '
b11111111111111111111111110001000 *
b10100 %
b10100 (
b0 ,
b1010011010101010100001000100000010000010010000000111101001111010010000001000010 -
#70
b1100100 #
b1100100 +
b11111111111111111111111111101100 %
b11111111111111111111111111101100 (
b10001100 ,
b10100110101010101000010001000000100000100100000001011010010000000101000001011010100001000101001 -
#80
b1001000 #
b1001000 +
b10 &
b10 )
b1001001 '
b1001001 *
b1111100 %
b1111100 (
b1100100 ,
b1010011010101010100001000100000001011010100000100100000001011010010000000101000001011010100001000101001 -
#90
b1111101 #
b1111101 +
b11 &
b11 )
1.
b1001000 ,
b10000010100111001000100 -
#100
b110101 #
b110101 +
b100 &
b100 )
b1111101 ,
b100111101010010 -
#110
b111110000000 #
b111110000000 +
b101 &
b101 )
b101 '
b101 *
b110101 ,
b10110000100111101010010 -
#120
b11 #
b11 +
b110 &
b110 )
b111110000000 ,
b10100110100110001001100 -
#130
b0 #
b0 +
b111 &
b111 )
b11 ,
b10100110101001001001100 -
