alu/alu.v
module alu(
    input signed [31:0] A, B,
    input [2:0] ALUControl,
    output reg signed [31:0] Result,
    output reg V, N, Zero
);

    always @(A, B, ALUControl) begin
        case (ALUControl)
            3'b000: begin // ADD
                Result = A + B;
            end
            3'b001: begin // SUB
                Result = A - B;
            end
            3'b010: begin // AND
                Result = A & B;
            end
            3'b011: begin // OR
                Result = A | B;
            end
            3'b100: begin // XOR
                Result = A ^ B;
            end
            3'b101: begin // SLL
                Result = A << 1;
            end
            3'b110: begin // SRL
                Result = A >> 1;
            end
            3'b111: begin // SLT
                if (A - B < 0)
                    // Set Less Than to 1
                    Result = 32'd1;
                else
                    // Set Less Than to 0
                    Result = 32'd0;
            end
            default:
                Result = 0;
        endcase

        if (A - B < 0) begin
            N <= 1;
            Zero <= 0;
        end else if (A - B == 0) begin
            Zero <= 1;
            N <= 0;
            V <= 0;
        end else begin
            V <= 0;
            N <= 0;
            Zero <= 0;
        end
    end
endmodule

alu/alu_tb.v
module alu_tb ();
    // test inputs
    reg signed [31:0] A, B;
    reg [2:0] ALUControl;

    // test outputs
    wire signed [31:0] Result;
    wire V, N, Zero;

    alu uut(
        A,
        B,
        ALUControl,
        Result,
        V,
        N,
        Zero
    );

    // Task for test assertion
    task assert_test(
        input [127:0] label,
        input signed [31:0] Expected
    );
        begin
            $display("==================================================");
            $display("%0s", label);
            $display("A: %d", A);
            $display("B: %d", B);
            $display("Expected: %d", Expected);
            $display("Result:   %d", Result);
            $display("Flags: V(%b), N(%b), Zero(%b)", V, N, Zero);
            
            if (Result != Expected) begin
                $display("❌ Test Failed! Expected: %0d, Got: %0d", Expected, Result);
            end else if (A - B < 0 && N != 1) begin
                $display("❌ Test Failed! Expected N: 1, Got N: %0d", N);
            end else if (A - B == 0 && Zero != 1) begin
                $display("❌ Test Failed! Expected Zero: 1, Got Zero: %0d", Zero);
            end else begin
                $display("✅ Test Passed!");
            end
        end
    endtask

    initial begin
        $dumpfile("alu_tb.vcd");
        $dumpvars(0, alu_tb);

        // ADD A > B
        ALUControl = 3'b000;
        A = 32'd124;
        B = 32'd73;
        #10
        assert_test("ADD +A +B", 124+73);

        // SUB A > B
        ALUControl = 3'b001;
        #10
        assert_test("SUB A > B", 124-73);

        // SUB A < B
        A = 32'd20;
        B = 32'd120;
        ALUControl = 3'b001;
        #10
        assert_test("SUB A < B", 20-120);

        // SUB A == B
        A = 32'd124;
        B = 32'd124;
        ALUControl = 3'b001;
        #10
        assert_test("SUB A == B", 124-124);

        // AND
        ALUControl = 3'b010;
        #10
        $display("==================================================");
        $display("AND Result: %0b", Result);

        // OR
        ALUControl = 3'b011;
        #10
        $display("OR Result: %0b", Result);

        // XOR
        ALUControl = 3'b100;
        #10
        $display("XOR Result: %0b", Result);

        // SHIFT LEFT LOGICAL
        ALUControl = 3'b101;
        #10
        $display("SLL Result: %0b", Result);

        // SHIFT RIGHT LOGICAL
        ALUControl = 3'b110;
        #10
        $display("SRL Result: %0b", Result);

        // A LESS THAN B
        ALUControl = 3'b111;
        #10
        $display("SLT Result: %0b", Result);

        $finish;
    end
endmodule

alu/alu_tb.vcd
$date
	Wed Feb 26 17:27:51 2025
$end
$version
	Icarus Verilog
$end
$timescale
	1s
$end
$scope module alu_tb $end
$var wire 1 ! Zero $end
$var wire 1 " V $end
$var wire 32 # Result [31:0] $end
$var wire 1 $ N $end
$var reg 32 % A [31:0] $end
$var reg 3 & ALUControl [2:0] $end
$var reg 32 ' B [31:0] $end
$scope module uut $end
$var wire 32 ( A [31:0] $end
$var wire 3 ) ALUControl [2:0] $end
$var wire 32 * B [31:0] $end
$var reg 1 $ N $end
$var reg 32 + Result [31:0] $end
$var reg 1 " V $end
$var reg 1 ! Zero $end
$upscope $end
$scope task assert_test $end
$var reg 32 , Expected [31:0] $end
$var reg 128 - label [127:0] $end
$upscope $end
$upscope $end
$enddefinitions $end
#0
$dumpvars
bx -
bx ,
b11000101 +
b1001001 *
b0 )
b1111100 (
b1001001 '
b0 &
b1111100 %
0$
b11000101 #
0"
0!
$end
#10
b110011 #
b110011 +
b1 &
b1 )
b11000101 ,
b10000010100010001000100001000000010101101000001001000000010101101000010 -
#20
1$
b11111111111111111111111110011100 #
b11111111111111111111111110011100 +
b1111000 '
b1111000 *
b10100 %
b10100 (
b110011 ,
b10100110101010101000010001000000100000100100000001111100010000001000010 -
#30
0$
1!
b0 #
b0 +
b1111100 '
b1111100 *
b1111100 %
b1111100 (
b11111111111111111111111110011100 ,
b10100110101010101000010001000000100000100100000001111000010000001000010 -
#40
b1111100 #
b1111100 +
b10 &
b10 )
b0 ,
b1010011010101010100001000100000010000010010000000111101001111010010000001000010 -
#50
b11 &
b11 )
#60
b0 #
b0 +
b100 &
b100 )
#70
b11111000 #
b11111000 +
b101 &
b101 )
#80
b111110 #
b111110 +
b110 &
b110 )
#90
b0 #
b0 +
b111 &
b111 )
