alu/alu.v
module alu(
    input [31:0] A, B,
    input [2:0] ALUControl,
    output reg [31:0] Result
);

    always @(A, B, ALUControl) begin
        case (ALUControl)
            3'b000: begin // ADD
                Result = A + B;
            end
            3'b001: begin // SUB
                Result = A - B;
            end
            3'b010: begin // AND
                Result = A & B;
            end
            3'b011: begin // OR
                Result = A | B;
            end
            3'b100: begin // XOR
                Result = A ^ B;
            end
            3'b101: begin // SLL
                Result = A << 1;
            end
            3'b110: begin // SRL
                Result = A >> 1;
            end
            3'b111: begin // SLT
                if (A - B < 0)
                    // Set Less Than to 1
                    Result = 32'd1;
                else
                    // Set Less Than to 0
                    Result = 32'd0;
            end
            default:
                Result = 0;
        endcase
    end
endmodule

alu/alu_tb.v
module alu_tb ();
    // test inputs
    reg [31:0] A, B;
    reg [2:0] ALUControl;

    // test outputs
    wire [31:0] Result;

    alu uut(
        A,
        B,
        ALUControl,
        Result
    );

    initial begin
        $dumpfile("alu_tb.vcd");
        $dumpvars(0, alu_tb);

        // ADD
        ALUControl = 3'b000;
        A = 32'd124;
        B = 32'd73;
        $display("A: %b", A);
        $display("B: %b", B);
        #10
        $display("ADD Result: %0b", Result);

        // SUB
        ALUControl = 3'b001;
        #10
        $display("SUB Result: %0b", Result);

        // AND
        ALUControl = 3'b010;
        #10
        $display("AND Result: %0b", Result);

        // OR
        ALUControl = 3'b011;
        #10
        $display("OR Result: %0b", Result);

        // XOR
        ALUControl = 3'b100;
        #10
        $display("XOR Result: %0b", Result);

        // SHIFT LEFT LOGICAL
        ALUControl = 3'b101;
        #10
        $display("SLL Result: %0b", Result);

        // SHIFT RIGHT LOGICAL
        ALUControl = 3'b110;
        #10
        $display("SRL Result: %0b", Result);

        // A LESS THAN B
        ALUControl = 3'b111;
        #10
        $display("SLT Result: %0b", Result);

        $finish;
    end
endmodule

alu/alu_tb.vcd
$date
	Sun Feb 23 21:29:46 2025
$end
$version
	Icarus Verilog
$end
$timescale
	1s
$end
$scope module alu_tb $end
$var wire 32 ! Result [31:0] $end
$var reg 32 " A [31:0] $end
$var reg 3 # ALUControl [2:0] $end
$var reg 32 $ B [31:0] $end
$scope module uut $end
$var wire 32 % A [31:0] $end
$var wire 3 & ALUControl [2:0] $end
$var wire 32 ' B [31:0] $end
$var reg 32 ( Result [31:0] $end
$upscope $end
$upscope $end
$enddefinitions $end
$comment Show the parameter values. $end
$dumpall
$end
#0
$dumpvars
b11000101 (
b1001001 '
b0 &
b1111100 %
b1001001 $
b0 #
b1111100 "
b11000101 !
$end
#10
b110011 !
b110011 (
b1 #
b1 &
#20
b1001000 !
b1001000 (
b10 #
b10 &
#30
b1111101 !
b1111101 (
b11 #
b11 &
#40
b110101 !
b110101 (
b100 #
b100 &
#50
b11111000 !
b11111000 (
b101 #
b101 &
#60
b111110 !
b111110 (
b110 #
b110 &
#70
b0 !
b0 (
b111 #
b111 &
