register_file/register_file.v
module register_file (
    input CLK, CLR, WE3,
    input [4:0] A1, A2, A3,
    input [31:0] WD3,
    output  [31:0] RD1, RD2
);
    // Instantiate an array of 32 32-bit registers
    reg [31:0] registers [31:0];

    // Initialize all registers to zero
    initial begin : init_regs
        integer i;
        for (i = 0; i < 32; i = i + 1) begin
            registers[i] = 32'd0;
        end
    end

    // Continuously assign reads based on A1 and A2 bit values
    assign RD1 = registers[A1];
    assign RD2 = registers[A2];

    // Logic happens on every positive edge of the clock
    always @ (posedge CLK) begin
        if (CLR) begin : reset_cycle
            // Reset all registers on clear
            integer i;
            for (i = 0; i < 32; i = i + 1) begin
                registers[i] <= 32'd0;
            end
        end else if (WE3 == 1'b1 && A3 != 5'd0) begin
            // Write if write enabled and not r0
            registers[A3] <= WD3; // Access register directly using A3 as the index
        end
    end
endmodule

register_file/register_file_tb.v
module register_file_tb ();
    // Test inputs
    reg CLK, CLR, WE3;
    reg [4:0] A1, A2, A3;
    reg [31:0] WD3;

    // Test outputs
    wire [31:0] RD1, RD2;

    // Instantiate unit under test
    register_file uut (
        CLK,
        CLR,
        WE3,
        A1,
        A2,
        A3,
        WD3,
        RD1,
        RD2
    );

    // Clock gen | clock flips every 5 ns
    always #5 CLK = ~CLK;

    initial begin
        // Create waveform file
        $dumpfile("register_file_tb.vcd");
        $dumpvars(0, register_file_tb);

        // Initialize clock, write enable, and select signals

        // 1. Initialize default no write
        CLK = 0;
        CLR = 1;
        WE3 = 0;
        WD3 = 32'd0;
        A1 = 5'd0;
        A2 = 5'd0;
        A3 = 5'd0;
        @(posedge CLK) // wait for one clock cycle low->high

        // // Reset clear
        CLR = 0;
        @(posedge CLK)

        // 2. Case: Write disabled, new write data
        WD3 = 32'hABCDEF0;
        @(posedge CLK)

        // 3. Case: Write enabled, write pointing to r0
        WE3 = 1;
        @(posedge CLK)

        // 4. Case: Write towards r1
        A3 = 5'b00001;
        @(posedge CLK)

        // 5. Case: Read towards r1 at 1
        A1 = 5'b00001;
        @(posedge CLK)

        // 6. Case: Write to r4, new write data, read r4 at 2
        A3 = 5'b00100;
        WD3 = 32'hFFFFFFFF;
        A2 = 5'b00100;
        @(posedge CLK)

        // 7. Switch read at 1
        A1 = 5'b10000;
        @(posedge CLK)

        $finish;
    end
endmodule

register_file/register_file_tb.vcd
$date
	Thu Feb 20 17:27:36 2025
$end
$version
	Icarus Verilog
$end
$timescale
	1s
$end
$scope module register_file_tb $end
$var wire 32 ! RD2 [31:0] $end
$var wire 32 " RD1 [31:0] $end
$var reg 5 # A1 [4:0] $end
$var reg 5 $ A2 [4:0] $end
$var reg 5 % A3 [4:0] $end
$var reg 1 & CLK $end
$var reg 1 ' CLR $end
$var reg 32 ( WD3 [31:0] $end
$var reg 1 ) WE3 $end
$scope module uut $end
$var wire 5 * A1 [4:0] $end
$var wire 5 + A2 [4:0] $end
$var wire 5 , A3 [4:0] $end
$var wire 1 & CLK $end
$var wire 1 ' CLR $end
$var wire 32 - RD1 [31:0] $end
$var wire 32 . RD2 [31:0] $end
$var wire 32 / WD3 [31:0] $end
$var wire 1 ) WE3 $end
$scope begin init_regs $end
$var integer 32 0 i [31:0] $end
$upscope $end
$scope begin reset_cycle $end
$var integer 32 1 i [31:0] $end
$upscope $end
$upscope $end
$upscope $end
$enddefinitions $end
$comment Show the parameter values. $end
$dumpall
$end
#0
$dumpvars
bx 1
b100000 0
b0 /
b0 .
b0 -
b0 ,
b0 +
b0 *
0)
b0 (
1'
0&
b0 %
b0 $
b0 #
b0 "
b0 !
$end
#5
0'
1&
#10
0&
#15
b1010101111001101111011110000 (
b1010101111001101111011110000 /
1&
#20
0&
#25
1)
1&
#30
0&
#35
b1 %
b1 ,
1&
#40
0&
#45
b1010101111001101111011110000 "
b1010101111001101111011110000 -
b1 #
b1 *
1&
#50
0&
#55
b100 $
b100 +
b11111111111111111111111111111111 (
b11111111111111111111111111111111 /
b100 %
b100 ,
1&
#60
0&
#65
b11111111111111111111111111111111 !
b11111111111111111111111111111111 .
b0 "
b0 -
b10000 #
b10000 *
1&
