register_file/register_file.v
`timescale 1ns/1ps

module register_file (
    input CLK, WE3,
    input [4:0] A1, A2, A3,
    input [31:0] WD3,
    output  [31:0] RD1, RD2
);
    // Instantiate an array of 32 32-bit registers
    reg [31:0] registers [31:0];

    // Initialize all registers to zero
    initial begin : init_regs
        integer i;
        for (i = 0; i < 32; i = i + 1) begin
            registers[i] = 32'h00000000;
        end
    end

    // Continuously assign reads based on A1 and A2 bit values
    assign RD1 = registers[A1];
    assign RD2 = registers[A2];

    // Logic happens on every positive edge of the clock
    always @ (posedge CLK) begin
        // Write only if write enabled
        if (WE3 == 1'b1 && A3 != 5'b00000) begin
            // Access register directly using A3 as the index
            registers[A3] <= WD3;
        end
    end
endmodule

register_file/register_file_tb.v
module register_file_tb ();
    // Test inputs
    reg CLK, WE3;
    reg [4:0] A1, A2, A3;
    reg [31:0] WD3;

    // Test outputs
    wire [31:0] RD1, RD2;

    // Instantiate unit under test
    register_file uut (
        CLK,
        WE3,
        A1,
        A2,
        A3,
        WD3,
        RD1,
        RD2
    );

    // Clock gen | clock flips every 5 ns
    always #5 CLK = ~CLK;

    initial begin
        // Create waveform file
        $dumpfile("register_file_tb.vcd");
        $dumpvars(0, register_file_tb);

        // Initialize clock, write enable, and select signals

        // 1. Nothing being written, default read/write select
        CLK = 0;
        WE3 = 0;
        WD3 = 32'h00000000;
        A1 = 5'b00000;
        A2 = 5'b00000;
        A3 = 5'b00000;
        #10

        // 2. Assign write data despite no enable
        WD3 = 32'hABCDEF0;
        #10 // wait for one clock cycle low->high

        // 3. Enable write data, should not update due to r0 select
        WE3 = 1;
        #10

        // 4. Change write select to r1
        A3 = 5'b00001;
        #10

        // 5. Change read select 1
        A1 = 5'b00001;
        #10

        // 6. Change write select to r4, change write data, change read 2
        WD3 = 32'hFFFFFFFF;
        A3 = 5'b00100;
        A2 = 5'b00100;
        #10

        // 7. Disable write
        WE3 = 0;
        #10

        $finish;
    end
endmodule

register_file/register_file_tb.vcd
$date
	Tue Feb 18 16:55:43 2025
$end
$version
	Icarus Verilog
$end
$timescale
	1ps
$end
$scope module register_file_tb $end
$var wire 32 ! RD2 [31:0] $end
$var wire 32 " RD1 [31:0] $end
$var reg 5 # A1 [4:0] $end
$var reg 5 $ A2 [4:0] $end
$var reg 5 % A3 [4:0] $end
$var reg 1 & CLK $end
$var reg 32 ' WD3 [31:0] $end
$var reg 1 ( WE3 $end
$scope module uut $end
$var wire 5 ) A1 [4:0] $end
$var wire 5 * A2 [4:0] $end
$var wire 5 + A3 [4:0] $end
$var wire 1 & CLK $end
$var wire 32 , RD1 [31:0] $end
$var wire 32 - RD2 [31:0] $end
$var wire 32 . WD3 [31:0] $end
$var wire 1 ( WE3 $end
$scope begin init_regs $end
$var integer 32 / i [31:0] $end
$upscope $end
$upscope $end
$upscope $end
$enddefinitions $end
$comment Show the parameter values. $end
$dumpall
$end
#0
$dumpvars
b100000 /
b0 .
b0 -
b0 ,
b0 +
b0 *
b0 )
0(
b0 '
0&
b0 %
b0 $
b0 #
b0 "
b0 !
$end
#5000
1&
#10000
0&
b1010101111001101111011110000 '
b1010101111001101111011110000 .
#15000
1&
#20000
0&
1(
#25000
1&
#30000
0&
b1 %
b1 +
#35000
1&
#40000
0&
b1010101111001101111011110000 "
b1010101111001101111011110000 ,
b1 #
b1 )
#45000
1&
#50000
0&
b100 $
b100 *
b100 %
b100 +
b11111111111111111111111111111111 '
b11111111111111111111111111111111 .
#55000
b11111111111111111111111111111111 !
b11111111111111111111111111111111 -
1&
#60000
0&
0(
